[
    {
        "name" : "iPhone 9",
        "categoryID" : 1,
        "description" : "An apple mobile which is nothing like apple",
        "cost" : 54900
    },
    {
        "name" : "iPhone X",
        "categoryID" : 1,
        "description" : "SIM-Free, Model A19211 6.5-inch Super Retina HD display with OLED technology A12 Bionic chip",
        "cost" : 89900
    },
    {
        "name" : "Samsung Universe 9",
        "categoryID" : 1,
        "description" : "Samsung new variant which goes beyond Galaxy to the Universe",
        "cost" : 124900
    },
    {
        "name" : "OPPOF19",
        "categoryID" : 1,
        "description" : "OPPO F19 is officially announced on April 2021.",
        "cost" : 28000
    },
    {
        "name" : "MacBook Pro",
        "categoryID" : 2,
        "description" : "MacBook Pro 2021 with mini-LED display may launch between September, November",
        "cost" : 174900
    },
    {
        "name" : "Samsung Galaxy Book",
        "categoryID" : 2,
        "description" : "Samsung Galaxy Book S (2020) Laptop With Intel Lakefield Chip, 8GB of RAM Launched",
        "cost" : 149900
    },
    {
        "name" : "Microsoft Surface Laptop 4",
        "categoryID" : 2,
        "description" : "Style and speed. Stand out on HD video calls backed by Studio Mics. Capture ideas on the vibrant touchscreen.",
        "cost" : 149900
    },
    {
        "name" : "perfume Oil",
        "categoryID" : 3,
        "description" : "Mega Discount, Impression of Acqua Di Gio by GiorgioArmani concentrated attar perfume Oil",
        "cost" : 1300
    },
    {
        "name" : "Brown Perfume",
        "categoryID" : 3,
        "description" : "Royal_Mirage Sport Brown Perfume for Men & Women - 120ml",
        "cost" : 4000
    },
    {
        "name" : "Hyaluronic Acid Serum",
        "categoryID" : 4,
        "description" : "LOreal Paris introduces Hyaluron Expert Replumping Serum formulated with 1.5% Hyaluronic Acid",
        "cost" : 1900
    },
    {
        "name" : "Tree Oil 30ml",
        "categoryID" : 4,
        "description" : "Tea tree oil contains a number of compounds, including terpinen-4-ol, that have been shown to kill certain bacteria",
        "cost" : 1200
    },
    {
        "name" : "Oil Free Moisturizer 100ml",
        "categoryID" : 4,
        "description" : "Dermive Oil Free Moisturizer with SPF 20 is specifically formulated with ceramides, hyaluronic acid & sunscreen.",
        "cost" : 4000
    },
    {
        "name" : "Skin Beauty Serum",
        "categoryID" : 4,
        "description" : "rorec collagen hyaluronic acid white face serum riceNet, weight: 15 m",
        "cost" : 4600
    },
    {
        "name" : "Daal Masoor 500 grams",
        "categoryID" : 5,
        "description" : "Fine quality Branded Product Keep in a cool and dry place",
        "cost" : 2000
    },
    {
        "name" : "Elbow Macaroni - 400 gm",
        "categoryID" : 5,
        "description" : "Product details of Bake Parlor Big Elbow Macaroni - 400 gm",
        "cost" : 1400
    },
    {
        "name" : "Orange Essence Food Flavour",
        "categoryID" : 5,
        "description" : "Specifications of Orange Essence Food Flavour For Cakes and Baking Food Item",
        "cost" : 1400
    },
    {
        "name" : "Plant Hanger For Home",
        "categoryID" : 6,
        "description" : "Boho Decor Plant Hanger For Home Wall Decoration Macrame Wall Hanging Shelf",
        "cost" : 4100
    },
    {
        "name" : "Flying Wooden Bird",
        "categoryID" : 6,
        "description" : "Package Include 6 Birds with Adhesive Tape Shape: 3D Shaped Wooden Birds Material: Wooden MDF, Laminated 3.5mm",
        "cost" : 5100
    },
    {
        "name" : "Key Holder",
        "categoryID" : 6,
        "description" : "Attractive DesignMetallic materialFour key hooksReliable & DurablePremium Quality",
        "cost" : 3000
    },
    {
        "name" : "Handcraft Chinese style",
        "categoryID" : 6,
        "description" : "Handcraft Chinese style art luxury palace hotel villa mansion home decor ceramic vase with brass fruit plate",
        "cost" : 6000
    },
    {
        "name" : "Mornadi Velvet Bed",
        "categoryID" : 7,
        "description" : "Mornadi Velvet Bed Base with Headboard Slats Support Classic Style Bedroom Furniture Bed Set",
        "cost" : 4000
    },
    {
        "name" : "Plastic Table",
        "categoryID" : 7,
        "description" : "Very good quality plastic table for multi purpose now in reasonable price",
        "cost" : 5000
    },
    {
        "name" : "Sleeve Shirt Womens",
        "categoryID" : 8,
        "description" : "Cotton Solid Color Professional Wear Sleeve Shirt Womens Work Blouses Wholesale Clothing Casual Plain Custom Top OEM Customized",
        "cost" : 9000
    },
    {
        "name" : "sublimation plain kids tank",
        "categoryID" : 8,
        "description" : "sublimation plain kids tank tops wholesale",
        "cost" : 10000
    },
    {
        "name" : "Women Sweaters Wool",
        "categoryID" : 8,
        "description" : "2021 Custom Winter Fall Zebra Knit Crop Top Women Sweaters Wool Mohair Cos Customize Crew Neck Women S Crop Top Sweater",
        "cost" : 60000
    },
    {
        "name" : "Rose Ring",
        "categoryID" : 9,
        "description" : "Brand: The Greetings Flower Colour: RedRing Colour: GoldenSize: Adjustable",
        "cost" : 10000
    },
    {
        "name" : "Rhinestone Korean Style Open Rings",
        "categoryID" : 9,
        "description" : "Fashion Jewellery 3Pcs Adjustable Pearl Rhinestone Korean Style Open Rings For Women",
        "cost" : 3000
    },
    {
        "name" : "Round Silver Frame Sun Glasses",
        "categoryID" : 10,
        "description" : "A pair of sunglasses can protect your eyes from being hurt. For car driving, vacation travel, outdoor activities, social gatherings",
        "cost" : 1900
    },
    {
        "name" : "Wiley X Night Vision Yellow Glasses",
        "categoryID" : 10,
        "description" : "Wiley X Night Vision Yellow Glasses for Riders - Night Vision Anti Fog Driving Glasses - Free Night Glass Cover - Shield Eyes From Dust and Virus- For Night Sport Matches",
        "cost" : 3000
    },
    {
        "name" : "Square Sunglasses",
        "categoryID" : 10,
        "description" : "Fashion Oversized Square Sunglasses Retro Gradient Big Frame Sunglasses For Women One Piece Gafas Shade Mirror Clear Lens 17059",
        "cost" : 2800
    },
    {
        "name" : "Bluetooth Aux",
        "categoryID" : 11,
        "description" : "Bluetooth Aux Bluetooth Car Aux Car Bluetooth Transmitter Aux Audio Receiver Handfree Car Bluetooth Music Receiver Universal 3.5mm Streaming A2DP Wireless Auto AUX Audio Adapter With Mic For Phone MP3",
        "cost" : 2500
    },
    {
        "name" : "Qualcomm original Car Charger",
        "categoryID" : 11,
        "description" : "best Quality CHarger , Highly Recommended to all best Quality CHarger , Highly Recommended to all",
        "cost" : 4000
    },
    {
        "name" : "Cycle Bike Glow",
        "categoryID" : 11,
        "description" : "Universal fitment and easy to install no special wires, can be easily installed and removed. Fits most standard tyre air stem valves of road, mountain bicycles, motocycles and cars. Bright led will turn on",
        "cost" : 3500
    },
    {
        "name" : "lighting ceiling kitchen",
        "categoryID" : 12,
        "description" : "Wholesale slim hanging decorative kid room lighting ceiling kitchen chandeliers pendant light modern",
        "cost" : 3000
    },
    {
        "name" : "Metal Ceramic Flower",
        "categoryID" : 12,
        "description" : "Metal Ceramic Flower Chandelier Home Lighting American Vintage Hanging Lighting Pendant Lamp",
        "cost" : 3500
    }
]